Metadata-Version: 1.1
Name: fcmcmp
Version: 0.1.0
Summary: A lightweight, flexible, and modern framework for annotating flow cytometry data.
Home-page: https://github.com/kalekundert/fcmcmp
Author: Kale Kundert
Author-email: kale.kundert@ucsf.edu
License: MIT
Keywords: fcmcmp
Platform: UNKNOWN
Classifier: Development Status :: 2 - Pre-Alpha
Classifier: Intended Audience :: Science/Research
Classifier: License :: OSI Approved :: MIT License
Classifier: Natural Language :: English
Classifier: Programming Language :: Python :: 3
Classifier: Programming Language :: Python :: 3.4
Classifier: Programming Language :: Python :: 3.5
Classifier: Topic :: Software Development :: Libraries
Classifier: Topic :: Scientific/Engineering :: Bio-Informatics
